scoreval/__init__.py
scoreval/scoreval.py
scoreval/test.py
score_eval-0.0.7.dist-info/LICENSE
score_eval-0.0.7.dist-info/METADATA
score_eval-0.0.7.dist-info/WHEEL
score_eval-0.0.7.dist-info/top_level.txt
score_eval-0.0.7.dist-info/RECORD
