Metadata-Version: 2.1
Name: score-eval
Version: 0.0.7
Summary: A visualization package for model score evaluation.
Author-email: Jingxiao Zhang <rex.zhang2016@foxmail.com>
Project-URL: Homepage, https://github.com/rexzhang2014/scoreval
Project-URL: Issues, https://github.com/rexzhang2014/scoreval/issues
Classifier: Programming Language :: Python :: 3
Classifier: License :: OSI Approved :: MIT License
Classifier: Operating System :: OS Independent
Requires-Python: >=3.8
License-File: LICENSE
